{
  "primaryBackground": "#2d2d2d",
  "secondaryBackground": "#00494f",
  "activityBarBackground": "#5a6054",
  "primaryForeground": "#e7e7e7",
  "secondaryForeground": "#969696",
  "classes": "#5c88df",
  "functions": "#d0ce57",
  "parameters": "#8adcff",
  "keywords": "#e1ac00",
  "variables": "#3bc4ff",
  "errors": "#ff8a8a",
  "strings": "#fffb30",
  "selectionHightlight": "#424450",
  "ansiBrightBlack": "#6272A4",
  "ansiBrightRed": "#FF6E6E",
  "ansiBrightGreen": "#69FF94",
  "ansiBrightYellow": "#FFFFA5",
  "ansiBrightBlue": "#D6AC",
  "ansiBrightMagenta": "#FF92DF",
  "ansiBrightCyan": "#A4FF",
  "ansiBrightWhite": "#FFFF",
  "ansiBlack": "#21222C",
  "ansiRed": "#FF5555",
  "ansiGreen": "#50FA7B",
  "ansiYellow": "#F1FA8C",
  "ansiBlue": "#BD93F9",
  "ansiMagenta": "#FF79C6",
  "ansiCyan": "#8BE9FD",
  "ansiWhite": "#F8F8F2"
}
